{
  "project_info": {
    "project_number": "262686868891",
    "project_id": "fix8-8d358",
    "storage_bucket": "fix8-8d358.firebasestorage.app"
  },
  "client": [
    {
      "client_info": {
        "mobilesdk_app_id": "1:262686868891:android:4756361893a9228a268d3e",
        "android_client_info": {
          "package_name": "com.example.login_and_signup"
        }
      },
      "oauth_client": [],
      "api_key": [
        {
          "current_key": "AIzaSyD7aCZ5qEOSTN_FYKXzWAQ2nT96Ggrw0aE"
        }
      ],
      "services": {
        "appinvite_service": {
          "other_platform_oauth_client": []
        }
      }
    }
  ],
  "configuration_version": "1"
}